zeugvars/__init__.py
zeugvars-0.2.8.dist-info/LICENSE
zeugvars-0.2.8.dist-info/METADATA
zeugvars-0.2.8.dist-info/WHEEL
zeugvars-0.2.8.dist-info/RECORD
